maintenance_server/__init__.py
maintenance_server/__main__.py
maintenance_server/maintenance.html
maintenance_server/maintenance_server.py
maintenance_server-2.0.0.dist-info/METADATA
maintenance_server-2.0.0.dist-info/WHEEL
maintenance_server-2.0.0.dist-info/top_level.txt
maintenance_server-2.0.0.dist-info/RECORD
