Metadata-Version: 2.1
Name: maintenance-server
Version: 2.0.0
Summary: Simple Maintenance Server returing simple html page
Home-page: https://gitlab.ndp-systemes.fr/python-libs/odoo_s3_fs
Author: Alexis Pasquier, NDP Systemes
Author-email: opensource@ndp-systemes.fr
License: GPLv3
Classifier: Programming Language :: Python :: 2.7
Classifier: Programming Language :: Python :: 3.6
Classifier: Programming Language :: Python :: 3.7
Classifier: Programming Language :: Python :: 3.8
Classifier: Programming Language :: Python :: 3.9
Classifier: Programming Language :: Python :: 3.10
Requires-Python: !=3.1.*,!=3.2.*,!=3.3.*,!=3.4.*,!=3.5.*,>=2.7
Requires-Dist: dataclasses (>=0.6) ; python_version < "3.7"
Requires-Dist: typing (==3.10.0.0) ; python_version <= "3"
Requires-Dist: Werkzeug (==0.16.1) ; python_version >= "3.6"
